{
  "$type": "Darkages.Types.ItemTemplate, Darkages.Server",
  "MiniScript": null,
  "ID": 0,
  "CanStack": false,
  "MaxStack": 0,
  "Image": 113,
  "DisplayImage": 32784,
  "ScriptName": "Helmet",
  "Gender": 2,
  "HealthModifer": null,
  "ManaModifer": null,
  "StrModifer": null,
  "IntModifer": null,
  "WisModifer": null,
  "ConModifer": null,
  "DexModifer": null,
  "AcModifer": {
    "$type": "Darkages.Types.StatusOperator, Darkages.Server",
    "Option": 1,
    "Value": 6
  },
  "MrModifer": null,
  "HitModifer": null,
  "DmgModifer": null,
  "SpellOperator": null,
  "OffenseElement": 0,
  "DefenseElement": 0,
  "CarryWeight": 0,
  "Flags": 125,
  "MaxDurability": 1500000,
  "Value": 5000000,
  "EquipmentSlot": 4,
  "NpcKey": "Suse",
  "Class": 1,
  "LevelRequired": 97,
  "DmgMin": 0,
  "DmgMax": 0,
  "DropRate": 0.0,
  "StageRequired": 0,
  "HasPants": false,
  "Color": 0,
  "WeaponScript": null,
  "Name": "Hy-Brasyl Plated Helmet",
  "Description": null,
  "Group": null
}