{
  "$type": "Darkages.Types.SpellTemplate, Darkages.Server",
  "Icon": 71,
  "MaxLevel": 100,
  "ScriptKey": "dia deo saighead",
  "MinLines": 1,
  "MaxLines": 9,
  "ManaCost": 350,
  "Text": "\u0000",
  "Debuff": null,
  "Buff": null,
  "TargetType": 2,
  "BaseLines": 2,
  "LevelRate": 0.06,
  "Sound": 26,
  "Animation": 288,
  "DamageExponent": 3200.0,
  "Pane": 0,
  "ElementalProperty": 5,
  "Prerequisites": null,
  "NpcKey": null,
  "TierLevel": 0,
  "TargetAnimation": 0,
  "IsTrap": false,
  "Name": "dia deo saighead",
  "Description": null,
  "Group": null
}